{"protocol": "MPC_protocol", "Mesh_topologies": "USnet.txt", "Q_c": 1, "p_op": 0.75, "loss_dB": 0.2, "timesteps": 5000, "reps": 1000, "users": ["22", "44", "42", "0", "43"], "ER": 0.2183406113537118, "links_used": 16.304, "network_data": {"directed": false, "multigraph": false, "graph": {}, "nodes": [{"Qc": 1, "entangled": false, "age": 0, "usage_count": 0, "usage_fraction": 0.0, "id": "0"}, {"Qc": 1, "entangled": false, "age": 0, "usage_count": 529, "usage_fraction": 0.529, "id": "1"}, {"Qc": 1, "entangled": false, "age": 0, "usage_count": 507, "usage_fraction": 0.507, "id": "2"}, {"Qc": 1, "entangled": false, "age": 0, "usage_count": 455, "usage_fraction": 0.455, "id": "3"}, {"Qc": 1, "entangled": false, "age": 0, "usage_count": 373, "usage_fraction": 0.373, "id": "9"}, {"Qc": 1, "entangled": false, "age": 0, "usage_count": 232, "usage_fraction": 0.232, "id": "4"}, {"Qc": 1, "entangled": false, "age": 0, "usage_count": 558, "usage_fraction": 0.558, "id": "7"}, {"Qc": 1, "entangled": false, "age": 0, "usage_count": 46, "usage_fraction": 0.046, "id": "5"}, {"Qc": 1, "entangled": false, "age": 0, "usage_count": 118, "usage_fraction": 0.118, "id": "6"}, {"Qc": 1, "entangled": false, "age": 0, "usage_count": 33, "usage_fraction": 0.033, "id": "8"}, {"Qc": 1, "entangled": false, "age": 0, "usage_count": 154, "usage_fraction": 0.154, "id": "12"}, {"Qc": 1, "entangled": false, "age": 0, "usage_count": 535, "usage_fraction": 0.535, "id": "10"}, {"Qc": 1, "entangled": false, "age": 0, "usage_count": 586, "usage_fraction": 0.586, "id": "11"}, {"Qc": 1, "entangled": false, "age": 0, "usage_count": 82, "usage_fraction": 0.082, "id": "13"}, {"Qc": 1, "entangled": false, "age": 0, "usage_count": 104, "usage_fraction": 0.104, "id": "20"}, {"Qc": 1, "entangled": false, "age": 0, "usage_count": 348, "usage_fraction": 0.348, "id": "19"}, {"Qc": 1, "entangled": false, "age": 0, "usage_count": 636, "usage_fraction": 0.636, "id": "17"}, {"Qc": 1, "entangled": false, "age": 0, "usage_count": 373, "usage_fraction": 0.373, "id": "18"}, {"Qc": 1, "entangled": false, "age": 0, "usage_count": 69, "usage_fraction": 0.069, "id": "14"}, {"Qc": 1, "entangled": false, "age": 0, "usage_count": 96, "usage_fraction": 0.096, "id": "15"}, {"Qc": 1, "entangled": false, "age": 0, "usage_count": 168, "usage_fraction": 0.168, "id": "16"}, {"Qc": 1, "entangled": false, "age": 0, "usage_count": 248, "usage_fraction": 0.248, "id": "21"}, {"Qc": 1, "entangled": false, "age": 0, "usage_count": 0, "usage_fraction": 0.0, "id": "22"}, {"Qc": 1, "entangled": false, "age": 0, "usage_count": 444, "usage_fraction": 0.444, "id": "23"}, {"Qc": 1, "entangled": false, "age": 0, "usage_count": 510, "usage_fraction": 0.51, "id": "24"}, {"Qc": 1, "entangled": false, "age": 0, "usage_count": 70, "usage_fraction": 0.07, "id": "25"}, {"Qc": 1, "entangled": false, "age": 0, "usage_count": 174, "usage_fraction": 0.174, "id": "31"}, {"Qc": 1, "entangled": false, "age": 0, "usage_count": 72, "usage_fraction": 0.072, "id": "32"}, {"Qc": 1, "entangled": false, "age": 0, "usage_count": 367, "usage_fraction": 0.367, "id": "30"}, {"Qc": 1, "entangled": false, "age": 0, "usage_count": 183, "usage_fraction": 0.183, "id": "26"}, {"Qc": 1, "entangled": false, "age": 0, "usage_count": 623, "usage_fraction": 0.623, "id": "28"}, {"Qc": 1, "entangled": false, "age": 0, "usage_count": 543, "usage_fraction": 0.543, "id": "27"}, {"Qc": 1, "entangled": false, "age": 0, "usage_count": 532, "usage_fraction": 0.532, "id": "41"}, {"Qc": 1, "entangled": false, "age": 0, "usage_count": 337, "usage_fraction": 0.337, "id": "29"}, {"Qc": 1, "entangled": false, "age": 0, "usage_count": 481, "usage_fraction": 0.481, "id": "40"}, {"Qc": 1, "entangled": false, "age": 0, "usage_count": 286, "usage_fraction": 0.286, "id": "39"}, {"Qc": 1, "entangled": false, "age": 0, "usage_count": 171, "usage_fraction": 0.171, "id": "37"}, {"Qc": 1, "entangled": false, "age": 0, "usage_count": 3, "usage_fraction": 0.003, "id": "33"}, {"Qc": 1, "entangled": false, "age": 0, "usage_count": 23, "usage_fraction": 0.023, "id": "35"}, {"Qc": 1, "entangled": false, "age": 0, "usage_count": 0, "usage_fraction": 0.0, "id": "34"}, {"Qc": 1, "entangled": false, "age": 0, "usage_count": 124, "usage_fraction": 0.124, "id": "36"}, {"Qc": 1, "entangled": false, "age": 0, "usage_count": 68, "usage_fraction": 0.068, "id": "38"}, {"Qc": 1, "entangled": false, "age": 0, "usage_count": 370, "usage_fraction": 0.37, "id": "45"}, {"Qc": 1, "entangled": false, "age": 0, "usage_count": 0, "usage_fraction": 0.0, "id": "42"}, {"Qc": 1, "entangled": false, "age": 0, "usage_count": 0, "usage_fraction": 0.0, "id": "44"}, {"Qc": 1, "entangled": false, "age": 0, "usage_count": 0, "usage_fraction": 0.0, "id": "43"}], "links": [{"length": 4.51, "Qc": 1, "p_edge": 0.6093422100418736, "entangled": true, "age": 0, "source": "0", "target": "1"}, {"length": 3.58, "Qc": 1, "p_edge": 0.6360060741672688, "entangled": true, "age": 0, "source": "0", "target": "2"}, {"length": 5.29, "Qc": 1, "p_edge": 0.5878428814017127, "entangled": true, "age": 0, "source": "1", "target": "3"}, {"length": 6.6, "Qc": 1, "p_edge": 0.5534281725968258, "entangled": false, "age": 0, "source": "1", "target": "9"}, {"length": 5.4, "Qc": 1, "p_edge": 0.584872582892444, "entangled": true, "age": 0, "source": "2", "target": "3"}, {"length": 8.94, "Qc": 1, "p_edge": 0.4968911519269369, "entangled": true, "age": 0, "source": "2", "target": "4"}, {"length": 3.04, "Qc": 1, "p_edge": 0.6520205193820622, "entangled": true, "age": 0, "source": "3", "target": "7"}, {"length": 2.97, "Qc": 1, "p_edge": 0.6541257766523215, "entangled": true, "age": 0, "source": "9", "target": "10"}, {"length": 9.09, "Qc": 1, "p_edge": 0.49347057729700544, "entangled": false, "age": 0, "source": "9", "target": "20"}, {"length": 3.35, "Qc": 1, "p_edge": 0.6427783839227772, "entangled": true, "age": 0, "source": "4", "target": "5"}, {"length": 4.42, "Qc": 1, "p_edge": 0.6118729630867559, "entangled": true, "age": 0, "source": "4", "target": "6"}, {"length": 4.77, "Qc": 1, "p_edge": 0.60208979099234, "entangled": false, "age": 0, "source": "4", "target": "7"}, {"length": 5.61, "Qc": 1, "p_edge": 0.5792436258429179, "entangled": true, "age": 0, "source": "7", "target": "6"}, {"length": 3.08, "Qc": 1, "p_edge": 0.6508205587433598, "entangled": true, "age": 0, "source": "7", "target": "10"}, {"length": 4.95, "Qc": 1, "p_edge": 0.5971195128129891, "entangled": false, "age": 0, "source": "7", "target": "11"}, {"length": 2.0, "Qc": 1, "p_edge": 0.6840081295169324, "entangled": true, "age": 0, "source": "5", "target": "6"}, {"length": 4.53, "Qc": 1, "p_edge": 0.608781243500419, "entangled": true, "age": 0, "source": "5", "target": "8"}, {"length": 4.22, "Qc": 1, "p_edge": 0.6175345539076009, "entangled": false, "age": 0, "source": "6", "target": "12"}, {"length": 3.81, "Qc": 1, "p_edge": 0.6293051174326021, "entangled": true, "age": 0, "source": "8", "target": "13"}, {"length": 4.61, "Qc": 1, "p_edge": 0.6065425368966331, "entangled": true, "age": 0, "source": "12", "target": "11"}, {"length": 4.68, "Qc": 1, "p_edge": 0.6045904228979183, "entangled": true, "age": 0, "source": "12", "target": "13"}, {"length": 5.5, "Qc": 1, "p_edge": 0.5821853374715188, "entangled": true, "age": 0, "source": "12", "target": "14"}, {"length": 2.1, "Qc": 1, "p_edge": 0.6808653976336393, "entangled": false, "age": 0, "source": "10", "target": "11"}, {"length": 3.96, "Qc": 1, "p_edge": 0.6249730114757375, "entangled": true, "age": 0, "source": "10", "target": "19"}, {"length": 7.64, "Qc": 1, "p_edge": 0.5275471284121855, "entangled": true, "age": 0, "source": "11", "target": "17"}, {"length": 7.43, "Qc": 1, "p_edge": 0.5326737107256495, "entangled": false, "age": 0, "source": "11", "target": "18"}, {"length": 5.79, "Qc": 1, "p_edge": 0.5744619437796659, "entangled": false, "age": 0, "source": "13", "target": "15"}, {"length": 3.74, "Qc": 1, "p_edge": 0.6313370307456094, "entangled": false, "age": 0, "source": "20", "target": "19"}, {"length": 3.68, "Qc": 1, "p_edge": 0.6330838916945765, "entangled": false, "age": 0, "source": "20", "target": "25"}, {"length": 3.89, "Qc": 1, "p_edge": 0.6269909371958853, "entangled": true, "age": 0, "source": "19", "target": "18"}, {"length": 7.7, "Qc": 1, "p_edge": 0.5260914738149784, "entangled": false, "age": 0, "source": "19", "target": "24"}, {"length": 3.04, "Qc": 1, "p_edge": 0.6520205193820622, "entangled": true, "age": 0, "source": "17", "target": "16"}, {"length": 3.0, "Qc": 1, "p_edge": 0.6532226924670604, "entangled": true, "age": 0, "source": "17", "target": "18"}, {"length": 2.01, "Qc": 1, "p_edge": 0.6836932046521254, "entangled": true, "age": 0, "source": "17", "target": "22"}, {"length": 4.47, "Qc": 1, "p_edge": 0.6104656943229511, "entangled": false, "age": 0, "source": "18", "target": "23"}, {"length": 3.73, "Qc": 1, "p_edge": 0.6316278391487095, "entangled": true, "age": 0, "source": "14", "target": "16"}, {"length": 3.95, "Qc": 1, "p_edge": 0.6252608884647257, "entangled": false, "age": 0, "source": "15", "target": "16"}, {"length": 5.58, "Qc": 1, "p_edge": 0.5800444335367478, "entangled": false, "age": 0, "source": "15", "target": "21"}, {"length": 3.42, "Qc": 1, "p_edge": 0.6407096474286362, "entangled": true, "age": 0, "source": "16", "target": "21"}, {"length": 3.38, "Qc": 1, "p_edge": 0.6418909659156179, "entangled": true, "age": 0, "source": "21", "target": "22"}, {"length": 4.72, "Qc": 1, "p_edge": 0.6034777513048502, "entangled": true, "age": 0, "source": "21", "target": "31"}, {"length": 4.12, "Qc": 1, "p_edge": 0.6203849638981006, "entangled": true, "age": 0, "source": "21", "target": "32"}, {"length": 5.03, "Qc": 1, "p_edge": 0.594923690568372, "entangled": false, "age": 0, "source": "22", "target": "23"}, {"length": 5.42, "Qc": 1, "p_edge": 0.5843341433348195, "entangled": true, "age": 0, "source": "22", "target": "30"}, {"length": 2.15, "Qc": 1, "p_edge": 0.67929945067365, "entangled": true, "age": 0, "source": "23", "target": "24"}, {"length": 2.93, "Qc": 1, "p_edge": 0.655331831338515, "entangled": true, "age": 0, "source": "24", "target": "26"}, {"length": 3.17, "Qc": 1, "p_edge": 0.6481287154849119, "entangled": false, "age": 0, "source": "24", "target": "28"}, {"length": 3.78, "Qc": 1, "p_edge": 0.6301751354307688, "entangled": true, "age": 0, "source": "25", "target": "26"}, {"length": 2.14, "Qc": 1, "p_edge": 0.6796123516739981, "entangled": false, "age": 0, "source": "31", "target": "30"}, {"length": 3.62, "Qc": 1, "p_edge": 0.6348355860732751, "entangled": true, "age": 0, "source": "31", "target": "37"}, {"length": 3.74, "Qc": 1, "p_edge": 0.6313370307456094, "entangled": true, "age": 0, "source": "32", "target": "33"}, {"length": 7.51, "Qc": 1, "p_edge": 0.5307148787698424, "entangled": false, "age": 0, "source": "32", "target": "35"}, {"length": 5.62, "Qc": 1, "p_edge": 0.5789769357076884, "entangled": false, "age": 0, "source": "32", "target": "37"}, {"length": 2.38, "Qc": 1, "p_edge": 0.6721423551462105, "entangled": true, "age": 0, "source": "30", "target": "29"}, {"length": 4.76, "Qc": 1, "p_edge": 0.6023671274419926, "entangled": false, "age": 0, "source": "26", "target": "27"}, {"length": 1.97, "Qc": 1, "p_edge": 0.6849537747486124, "entangled": true, "age": 0, "source": "28", "target": "27"}, {"length": 3.08, "Qc": 1, "p_edge": 0.6508205587433598, "entangled": true, "age": 0, "source": "28", "target": "29"}, {"length": 8.13, "Qc": 1, "p_edge": 0.5157761587081566, "entangled": true, "age": 0, "source": "28", "target": "40"}, {"length": 3.6, "Qc": 1, "p_edge": 0.6354205606054473, "entangled": true, "age": 0, "source": "27", "target": "41"}, {"length": 7.09, "Qc": 1, "p_edge": 0.5410797284443567, "entangled": true, "age": 0, "source": "41", "target": "40"}, {"length": 3.76, "Qc": 1, "p_edge": 0.630755815551925, "entangled": false, "age": 0, "source": "41", "target": "42"}, {"length": 4.49, "Qc": 1, "p_edge": 0.6099036934906148, "entangled": true, "age": 0, "source": "41", "target": "44"}, {"length": 8.19, "Qc": 1, "p_edge": 0.5143529836094446, "entangled": true, "age": 0, "source": "29", "target": "39"}, {"length": 3.27, "Qc": 1, "p_edge": 0.6451508345347677, "entangled": true, "age": 0, "source": "40", "target": "39"}, {"length": 2.66, "Qc": 1, "p_edge": 0.6635310696528981, "entangled": true, "age": 0, "source": "40", "target": "45"}, {"length": 2.51, "Qc": 1, "p_edge": 0.6681304473006153, "entangled": true, "age": 0, "source": "39", "target": "36"}, {"length": 4.54, "Qc": 1, "p_edge": 0.6085009539211974, "entangled": true, "age": 0, "source": "39", "target": "38"}, {"length": 3.46, "Qc": 1, "p_edge": 0.6395305030077215, "entangled": true, "age": 0, "source": "37", "target": "36"}, {"length": 3.17, "Qc": 1, "p_edge": 0.6481287154849119, "entangled": true, "age": 0, "source": "37", "target": "38"}, {"length": 5.62, "Qc": 1, "p_edge": 0.5789769357076884, "entangled": true, "age": 0, "source": "33", "target": "34"}, {"length": 3.93, "Qc": 1, "p_edge": 0.6258370403121319, "entangled": true, "age": 0, "source": "33", "target": "35"}, {"length": 4.03, "Qc": 1, "p_edge": 0.6229615803059421, "entangled": true, "age": 0, "source": "35", "target": "34"}, {"length": 3.21, "Qc": 1, "p_edge": 0.6469359172151092, "entangled": false, "age": 0, "source": "35", "target": "36"}, {"length": 1.78, "Qc": 1, "p_edge": 0.6909732957514166, "entangled": true, "age": 0, "source": "45", "target": "44"}, {"length": 3.52, "Qc": 1, "p_edge": 0.6377658539998513, "entangled": true, "age": 0, "source": "42", "target": "43"}, {"length": 3.66, "Qc": 1, "p_edge": 0.6336672521133906, "entangled": true, "age": 0, "source": "44", "target": "43"}]}}