{"protocol": "MPG_protocol", "Mesh_topologies": "USnet.txt", "Q_c": 1, "p_op": 0.25, "loss_dB": 0.2, "timesteps": 5000, "reps": 1000, "users": ["22", "44", "42", "0", "43"], "ER": 0.0, "links_used": 0.0, "network_data": {"directed": false, "multigraph": false, "graph": {}, "nodes": [{"Qc": 1, "entangled": false, "age": 1, "usage_count": 0, "usage_fraction": 0.0, "id": "0"}, {"Qc": 1, "entangled": false, "age": 0, "usage_count": 0, "usage_fraction": 0.0, "id": "1"}, {"Qc": 1, "entangled": false, "age": 0, "usage_count": 0, "usage_fraction": 0.0, "id": "2"}, {"Qc": 1, "entangled": false, "age": 0, "usage_count": 0, "usage_fraction": 0.0, "id": "3"}, {"Qc": 1, "entangled": false, "age": 0, "usage_count": 0, "usage_fraction": 0.0, "id": "9"}, {"Qc": 1, "entangled": false, "age": 0, "usage_count": 0, "usage_fraction": 0.0, "id": "4"}, {"Qc": 1, "entangled": false, "age": 0, "usage_count": 0, "usage_fraction": 0.0, "id": "7"}, {"Qc": 1, "entangled": false, "age": 0, "usage_count": 0, "usage_fraction": 0.0, "id": "5"}, {"Qc": 1, "entangled": false, "age": 0, "usage_count": 0, "usage_fraction": 0.0, "id": "6"}, {"Qc": 1, "entangled": false, "age": 0, "usage_count": 0, "usage_fraction": 0.0, "id": "8"}, {"Qc": 1, "entangled": false, "age": 0, "usage_count": 0, "usage_fraction": 0.0, "id": "12"}, {"Qc": 1, "entangled": false, "age": 0, "usage_count": 0, "usage_fraction": 0.0, "id": "10"}, {"Qc": 1, "entangled": false, "age": 0, "usage_count": 0, "usage_fraction": 0.0, "id": "11"}, {"Qc": 1, "entangled": false, "age": 0, "usage_count": 0, "usage_fraction": 0.0, "id": "13"}, {"Qc": 1, "entangled": false, "age": 0, "usage_count": 0, "usage_fraction": 0.0, "id": "20"}, {"Qc": 1, "entangled": false, "age": 0, "usage_count": 0, "usage_fraction": 0.0, "id": "19"}, {"Qc": 1, "entangled": false, "age": 0, "usage_count": 0, "usage_fraction": 0.0, "id": "17"}, {"Qc": 1, "entangled": false, "age": 0, "usage_count": 0, "usage_fraction": 0.0, "id": "18"}, {"Qc": 1, "entangled": false, "age": 0, "usage_count": 0, "usage_fraction": 0.0, "id": "14"}, {"Qc": 1, "entangled": false, "age": 0, "usage_count": 0, "usage_fraction": 0.0, "id": "15"}, {"Qc": 1, "entangled": false, "age": 0, "usage_count": 0, "usage_fraction": 0.0, "id": "16"}, {"Qc": 1, "entangled": false, "age": 0, "usage_count": 0, "usage_fraction": 0.0, "id": "21"}, {"Qc": 1, "entangled": false, "age": 0, "usage_count": 0, "usage_fraction": 0.0, "id": "22"}, {"Qc": 1, "entangled": false, "age": 0, "usage_count": 0, "usage_fraction": 0.0, "id": "23"}, {"Qc": 1, "entangled": false, "age": 0, "usage_count": 0, "usage_fraction": 0.0, "id": "24"}, {"Qc": 1, "entangled": false, "age": 0, "usage_count": 0, "usage_fraction": 0.0, "id": "25"}, {"Qc": 1, "entangled": false, "age": 0, "usage_count": 0, "usage_fraction": 0.0, "id": "31"}, {"Qc": 1, "entangled": false, "age": 0, "usage_count": 0, "usage_fraction": 0.0, "id": "32"}, {"Qc": 1, "entangled": false, "age": 0, "usage_count": 0, "usage_fraction": 0.0, "id": "30"}, {"Qc": 1, "entangled": false, "age": 0, "usage_count": 0, "usage_fraction": 0.0, "id": "26"}, {"Qc": 1, "entangled": false, "age": 0, "usage_count": 0, "usage_fraction": 0.0, "id": "28"}, {"Qc": 1, "entangled": false, "age": 0, "usage_count": 0, "usage_fraction": 0.0, "id": "27"}, {"Qc": 1, "entangled": false, "age": 0, "usage_count": 0, "usage_fraction": 0.0, "id": "41"}, {"Qc": 1, "entangled": false, "age": 0, "usage_count": 0, "usage_fraction": 0.0, "id": "29"}, {"Qc": 1, "entangled": false, "age": 0, "usage_count": 0, "usage_fraction": 0.0, "id": "40"}, {"Qc": 1, "entangled": false, "age": 0, "usage_count": 0, "usage_fraction": 0.0, "id": "39"}, {"Qc": 1, "entangled": false, "age": 0, "usage_count": 0, "usage_fraction": 0.0, "id": "37"}, {"Qc": 1, "entangled": false, "age": 0, "usage_count": 0, "usage_fraction": 0.0, "id": "33"}, {"Qc": 1, "entangled": false, "age": 0, "usage_count": 0, "usage_fraction": 0.0, "id": "35"}, {"Qc": 1, "entangled": false, "age": 0, "usage_count": 0, "usage_fraction": 0.0, "id": "34"}, {"Qc": 1, "entangled": false, "age": 0, "usage_count": 0, "usage_fraction": 0.0, "id": "36"}, {"Qc": 1, "entangled": false, "age": 0, "usage_count": 0, "usage_fraction": 0.0, "id": "38"}, {"Qc": 1, "entangled": false, "age": 0, "usage_count": 0, "usage_fraction": 0.0, "id": "45"}, {"Qc": 1, "entangled": false, "age": 0, "usage_count": 0, "usage_fraction": 0.0, "id": "42"}, {"Qc": 1, "entangled": false, "age": 1, "usage_count": 0, "usage_fraction": 0.0, "id": "44"}, {"Qc": 1, "entangled": false, "age": 0, "usage_count": 0, "usage_fraction": 0.0, "id": "43"}], "links": [{"length": 4.51, "Qc": 1, "p_edge": 0.20311407001395787, "entangled": false, "age": 0, "source": "0", "target": "1"}, {"length": 3.58, "Qc": 1, "p_edge": 0.21200202472242297, "entangled": true, "age": 0, "source": "0", "target": "2"}, {"length": 5.29, "Qc": 1, "p_edge": 0.19594762713390423, "entangled": false, "age": 0, "source": "1", "target": "3"}, {"length": 6.6, "Qc": 1, "p_edge": 0.18447605753227525, "entangled": false, "age": 0, "source": "1", "target": "9"}, {"length": 5.4, "Qc": 1, "p_edge": 0.19495752763081467, "entangled": true, "age": 0, "source": "2", "target": "3"}, {"length": 8.94, "Qc": 1, "p_edge": 0.16563038397564564, "entangled": false, "age": 0, "source": "2", "target": "4"}, {"length": 3.04, "Qc": 1, "p_edge": 0.21734017312735407, "entangled": false, "age": 0, "source": "3", "target": "7"}, {"length": 2.97, "Qc": 1, "p_edge": 0.21804192555077384, "entangled": false, "age": 0, "source": "9", "target": "10"}, {"length": 9.09, "Qc": 1, "p_edge": 0.16449019243233515, "entangled": false, "age": 0, "source": "9", "target": "20"}, {"length": 3.35, "Qc": 1, "p_edge": 0.2142594613075924, "entangled": false, "age": 0, "source": "4", "target": "5"}, {"length": 4.42, "Qc": 1, "p_edge": 0.20395765436225194, "entangled": false, "age": 0, "source": "4", "target": "6"}, {"length": 4.77, "Qc": 1, "p_edge": 0.20069659699744666, "entangled": false, "age": 0, "source": "4", "target": "7"}, {"length": 5.61, "Qc": 1, "p_edge": 0.19308120861430594, "entangled": false, "age": 0, "source": "7", "target": "6"}, {"length": 3.08, "Qc": 1, "p_edge": 0.2169401862477866, "entangled": false, "age": 0, "source": "7", "target": "10"}, {"length": 4.95, "Qc": 1, "p_edge": 0.1990398376043297, "entangled": false, "age": 0, "source": "7", "target": "11"}, {"length": 2.0, "Qc": 1, "p_edge": 0.22800270983897744, "entangled": false, "age": 0, "source": "5", "target": "6"}, {"length": 4.53, "Qc": 1, "p_edge": 0.2029270811668063, "entangled": false, "age": 0, "source": "5", "target": "8"}, {"length": 4.22, "Qc": 1, "p_edge": 0.20584485130253363, "entangled": false, "age": 0, "source": "6", "target": "12"}, {"length": 3.81, "Qc": 1, "p_edge": 0.20976837247753405, "entangled": false, "age": 0, "source": "8", "target": "13"}, {"length": 4.61, "Qc": 1, "p_edge": 0.202180845632211, "entangled": false, "age": 0, "source": "12", "target": "11"}, {"length": 4.68, "Qc": 1, "p_edge": 0.20153014096597277, "entangled": false, "age": 0, "source": "12", "target": "13"}, {"length": 5.5, "Qc": 1, "p_edge": 0.19406177915717293, "entangled": true, "age": 0, "source": "12", "target": "14"}, {"length": 2.1, "Qc": 1, "p_edge": 0.22695513254454644, "entangled": false, "age": 0, "source": "10", "target": "11"}, {"length": 3.96, "Qc": 1, "p_edge": 0.20832433715857918, "entangled": true, "age": 0, "source": "10", "target": "19"}, {"length": 7.64, "Qc": 1, "p_edge": 0.17584904280406183, "entangled": false, "age": 0, "source": "11", "target": "17"}, {"length": 7.43, "Qc": 1, "p_edge": 0.1775579035752165, "entangled": false, "age": 0, "source": "11", "target": "18"}, {"length": 5.79, "Qc": 1, "p_edge": 0.19148731459322196, "entangled": false, "age": 0, "source": "13", "target": "15"}, {"length": 3.74, "Qc": 1, "p_edge": 0.21044567691520316, "entangled": false, "age": 0, "source": "20", "target": "19"}, {"length": 3.68, "Qc": 1, "p_edge": 0.21102796389819214, "entangled": false, "age": 0, "source": "20", "target": "25"}, {"length": 3.89, "Qc": 1, "p_edge": 0.20899697906529507, "entangled": false, "age": 0, "source": "19", "target": "18"}, {"length": 7.7, "Qc": 1, "p_edge": 0.1753638246049928, "entangled": false, "age": 0, "source": "19", "target": "24"}, {"length": 3.04, "Qc": 1, "p_edge": 0.21734017312735407, "entangled": true, "age": 0, "source": "17", "target": "16"}, {"length": 3.0, "Qc": 1, "p_edge": 0.21774089748902015, "entangled": false, "age": 0, "source": "17", "target": "18"}, {"length": 2.01, "Qc": 1, "p_edge": 0.2278977348840418, "entangled": false, "age": 0, "source": "17", "target": "22"}, {"length": 4.47, "Qc": 1, "p_edge": 0.203488564774317, "entangled": false, "age": 0, "source": "18", "target": "23"}, {"length": 3.73, "Qc": 1, "p_edge": 0.2105426130495698, "entangled": false, "age": 0, "source": "14", "target": "16"}, {"length": 3.95, "Qc": 1, "p_edge": 0.2084202961549086, "entangled": false, "age": 0, "source": "15", "target": "16"}, {"length": 5.58, "Qc": 1, "p_edge": 0.1933481445122493, "entangled": false, "age": 0, "source": "15", "target": "21"}, {"length": 3.42, "Qc": 1, "p_edge": 0.2135698824762121, "entangled": true, "age": 0, "source": "16", "target": "21"}, {"length": 3.38, "Qc": 1, "p_edge": 0.21396365530520597, "entangled": false, "age": 0, "source": "21", "target": "22"}, {"length": 4.72, "Qc": 1, "p_edge": 0.20115925043495003, "entangled": false, "age": 0, "source": "21", "target": "31"}, {"length": 4.12, "Qc": 1, "p_edge": 0.20679498796603354, "entangled": false, "age": 0, "source": "21", "target": "32"}, {"length": 5.03, "Qc": 1, "p_edge": 0.19830789685612402, "entangled": false, "age": 0, "source": "22", "target": "23"}, {"length": 5.42, "Qc": 1, "p_edge": 0.19477804777827318, "entangled": false, "age": 0, "source": "22", "target": "30"}, {"length": 2.15, "Qc": 1, "p_edge": 0.22643315022455002, "entangled": false, "age": 0, "source": "23", "target": "24"}, {"length": 2.93, "Qc": 1, "p_edge": 0.218443943779505, "entangled": false, "age": 0, "source": "24", "target": "26"}, {"length": 3.17, "Qc": 1, "p_edge": 0.2160429051616373, "entangled": false, "age": 0, "source": "24", "target": "28"}, {"length": 3.78, "Qc": 1, "p_edge": 0.21005837847692294, "entangled": true, "age": 0, "source": "25", "target": "26"}, {"length": 2.14, "Qc": 1, "p_edge": 0.22653745055799937, "entangled": false, "age": 0, "source": "31", "target": "30"}, {"length": 3.62, "Qc": 1, "p_edge": 0.211611862024425, "entangled": false, "age": 0, "source": "31", "target": "37"}, {"length": 3.74, "Qc": 1, "p_edge": 0.21044567691520316, "entangled": true, "age": 0, "source": "32", "target": "33"}, {"length": 7.51, "Qc": 1, "p_edge": 0.17690495958994745, "entangled": false, "age": 0, "source": "32", "target": "35"}, {"length": 5.62, "Qc": 1, "p_edge": 0.1929923119025628, "entangled": true, "age": 0, "source": "32", "target": "37"}, {"length": 2.38, "Qc": 1, "p_edge": 0.22404745171540347, "entangled": false, "age": 0, "source": "30", "target": "29"}, {"length": 4.76, "Qc": 1, "p_edge": 0.2007890424806642, "entangled": true, "age": 0, "source": "26", "target": "27"}, {"length": 1.97, "Qc": 1, "p_edge": 0.22831792491620415, "entangled": false, "age": 0, "source": "28", "target": "27"}, {"length": 3.08, "Qc": 1, "p_edge": 0.2169401862477866, "entangled": false, "age": 0, "source": "28", "target": "29"}, {"length": 8.13, "Qc": 1, "p_edge": 0.17192538623605222, "entangled": true, "age": 0, "source": "28", "target": "40"}, {"length": 3.6, "Qc": 1, "p_edge": 0.2118068535351491, "entangled": false, "age": 0, "source": "27", "target": "41"}, {"length": 7.09, "Qc": 1, "p_edge": 0.18035990948145225, "entangled": true, "age": 0, "source": "41", "target": "40"}, {"length": 3.76, "Qc": 1, "p_edge": 0.2102519385173083, "entangled": true, "age": 0, "source": "41", "target": "42"}, {"length": 4.49, "Qc": 1, "p_edge": 0.20330123116353827, "entangled": true, "age": 0, "source": "41", "target": "44"}, {"length": 8.19, "Qc": 1, "p_edge": 0.17145099453648152, "entangled": false, "age": 0, "source": "29", "target": "39"}, {"length": 3.27, "Qc": 1, "p_edge": 0.21505027817825592, "entangled": false, "age": 0, "source": "40", "target": "39"}, {"length": 2.66, "Qc": 1, "p_edge": 0.2211770232176327, "entangled": false, "age": 0, "source": "40", "target": "45"}, {"length": 2.51, "Qc": 1, "p_edge": 0.22271014910020512, "entangled": false, "age": 0, "source": "39", "target": "36"}, {"length": 4.54, "Qc": 1, "p_edge": 0.20283365130706582, "entangled": true, "age": 0, "source": "39", "target": "38"}, {"length": 3.46, "Qc": 1, "p_edge": 0.21317683433590717, "entangled": false, "age": 0, "source": "37", "target": "36"}, {"length": 3.17, "Qc": 1, "p_edge": 0.2160429051616373, "entangled": false, "age": 0, "source": "37", "target": "38"}, {"length": 5.62, "Qc": 1, "p_edge": 0.1929923119025628, "entangled": false, "age": 0, "source": "33", "target": "34"}, {"length": 3.93, "Qc": 1, "p_edge": 0.20861234677071064, "entangled": false, "age": 0, "source": "33", "target": "35"}, {"length": 4.03, "Qc": 1, "p_edge": 0.20765386010198067, "entangled": false, "age": 0, "source": "35", "target": "34"}, {"length": 3.21, "Qc": 1, "p_edge": 0.21564530573836976, "entangled": true, "age": 0, "source": "35", "target": "36"}, {"length": 1.78, "Qc": 1, "p_edge": 0.2303244319171389, "entangled": false, "age": 0, "source": "45", "target": "44"}, {"length": 3.52, "Qc": 1, "p_edge": 0.21258861799995044, "entangled": false, "age": 0, "source": "42", "target": "43"}, {"length": 3.66, "Qc": 1, "p_edge": 0.2112224173711302, "entangled": false, "age": 0, "source": "44", "target": "43"}]}}